{"facets": {"unique identifier": 3, "Commons:Depicts": 21, "chronology": 5, "work": 9, "version, edition, or translation": 9, "data transmission": 2, "data retrieval": 2, "data storage": 2, "human": 14, "P1365": 1, "P805": 1, "P1366": 1, "occurrence": 4, "politics": 1, "website": 1, "P1326": 1, "P1480": 1, "work of fiction": 1, "Wikidata property definition": 8, "corporation": 1, "Wikimedia Commons": 1, "P1310": 1, "P1013": 1, "P3294": 1, "P560": 1, "taxon": 2, "name": 2, "geographic location": 2, "transitive relation": 3, "P4155": 1, "P2096": 1, "road transport": 1, "rail transport": 1, "art": 4, "art collection": 4, "award": 1, "P155": 1, "sports organization": 1, "sport": 2, "Wikipedia:Citing sources": 3, "archival science": 2, "P3831": 1, "human geography": 1, "ownership": 1, "asymmetric relation": 2, "asymmetry property": 2, "LGBT": 1, "P659": 1, "P156": 1, "P2241": 1, "production": 1, "P2868": 1, "P2916": 1, "age of a person": 1, "physical quantity": 1}, "total_facets": 122, "unique_facets": 37, "properties_without_facets": 18}